{"elonmusk": {"pinned_tweet_id": "1995277243325850034", "latest_tweet_id": "1995234109120303471"}, "nhat1122319": {"pinned_tweet_id": null, "latest_tweet_id": "1995277243325850034"}, "tommyzz8": {"pinned_tweet_id": null, "latest_tweet_id": "1988065931696939464"}, "BarrySilbert": {"pinned_tweet_id": null, "latest_tweet_id": "1996170035786850652"}, "metaproph3t": {"pinned_tweet_id": null, "latest_tweet_id": "1995915238563070369"}, "biancoresearch": {"pinned_tweet_id": "1942569031275536451", "latest_tweet_id": "1996434470241435846"}, "EricBalchunas": {"pinned_tweet_id": "1507696286870523913", "latest_tweet_id": "1996303864006398194"}}